{
  "conditions": [
    {
      "condition": "minecraft:alternative",
      "terms": [
        {
          "condition": "forge:loot_table_id",
          "loot_table_id": "minecraft:chests/simple_dungeon"
        },
        {
          "condition": "forge:loot_table_id",
          "loot_table_id": "minecraft:chests/desert_pyramid"
        },
        {
          "condition": "forge:loot_table_id",
          "loot_table_id": "minecraft:chests/ruined_portal"
        },
        {
          "condition": "forge:loot_table_id",
          "loot_table_id": "minecraft:chests/village/village_armorer"
        }
      ]
    }
  ],
  "type": "copperized:chance_item",
  "item": "copperized:copper_helmet",
  "chance": 0.10,
  "minAmount": 1,
  "maxAmount": 1,
  "unique": true
}